demo_widgets/__init__.py
demo_widgets/_frontend.py
demo_widgets/_version.py
demo_widgets/labextension/build_log.json
demo_widgets/labextension/package.json
demo_widgets/labextension/static/lib_index_js.844e67bbf9b8e1c6dc58.js
demo_widgets/labextension/static/lib_index_js.844e67bbf9b8e1c6dc58.js.map
demo_widgets/labextension/static/lib_plugin_js.3df00e5afe9e41c72128.js
demo_widgets/labextension/static/lib_plugin_js.3df00e5afe9e41c72128.js.map
demo_widgets/labextension/static/lib_widgets_example_widget_js-lib_widgets_stock_chart_widget_js-lib_widgets_stock_list_widget-8e235a.f4c447e1cc91e213aac2.js
demo_widgets/labextension/static/lib_widgets_example_widget_js-lib_widgets_stock_chart_widget_js-lib_widgets_stock_list_widget-8e235a.f4c447e1cc91e213aac2.js.map
demo_widgets/labextension/static/remoteEntry.961342a11619b12bc9d3.js
demo_widgets/labextension/static/remoteEntry.961342a11619b12bc9d3.js.map
demo_widgets/labextension/static/style.js
demo_widgets/labextension/static/vendors-node_modules_css-loader_dist_runtime_api_js-node_modules_style-loader_dist_runtime_in-e93230.0148f04a477b2984f924.js
demo_widgets/labextension/static/vendors-node_modules_css-loader_dist_runtime_api_js-node_modules_style-loader_dist_runtime_in-e93230.0148f04a477b2984f924.js.map
demo_widgets/labextension/static/vendors-node_modules_jquery_dist_jquery_js.bc36ed11f07da4829524.js
demo_widgets/labextension/static/vendors-node_modules_jquery_dist_jquery_js.bc36ed11f07da4829524.js.map
demo_widgets/labextension/static/vendors-node_modules_underscore_modules_index-all_js.87b689fdf8d34e911431.js
demo_widgets/labextension/static/vendors-node_modules_underscore_modules_index-all_js.87b689fdf8d34e911431.js.map
demo_widgets/nbextension/extension.js
demo_widgets/nbextension/index.js
demo_widgets/nbextension/index.js.LICENSE.txt
demo_widgets/nbextension/index.js.map
demo_widgets/tests/__init__.py
demo_widgets/tests/conftest.py
demo_widgets/tests/test_example.py
demo_widgets/tests/test_nbextension_path.py
demo_widgets-0.1.4.dist-info/METADATA
demo_widgets-0.1.4.dist-info/WHEEL
demo_widgets-0.1.4.dist-info/licenses/LICENSE.txt
demo_widgets-0.1.4.dist-info/RECORD
